.gitignore
.pre-commit-config.yaml
.pylintrc
.readthedocs.yaml
CODE_OF_CONDUCT.md
LICENSE
README.rst
README.rst.license
pyproject.toml
requirements.txt
setup.py
sparkfun_serlcd.py
.github/PULL_REQUEST_TEMPLATE/adafruit_circuitpython_pr.md
.github/workflows/build.yml
.github/workflows/failure-help-text.yml
.github/workflows/release.yml
LICENSES/CC-BY-4.0.txt
LICENSES/MIT.txt
LICENSES/Unlicense.txt
docs/api.rst
docs/api.rst.license
docs/conf.py
docs/examples.rst
docs/examples.rst.license
docs/index.rst
docs/index.rst.license
docs/requirements.txt
docs/_static/favicon.ico
docs/_static/favicon.ico.license
examples/example10_turn_off_display.py
examples/example11_text_direction.py
examples/example12_display_input_text.py
examples/example13_fast_backlight.py
examples/example14_show_firmware_version.py
examples/example15_system_messages.py
examples/example16_splash_screen.py
examples/example1_hello_world.py
examples/example2_backlight.py
examples/example3_cursor_position.py
examples/example4_move_cursor.py
examples/example5_enable_cursor.py
examples/example6_blink_cursor.py
examples/example7_scroll_display.py
examples/example8_autoscroll_text.py
examples/example9_custom_characters.py
examples/serlcd_simpletest.py
sparkfun_circuitpython_serlcd.egg-info/PKG-INFO
sparkfun_circuitpython_serlcd.egg-info/SOURCES.txt
sparkfun_circuitpython_serlcd.egg-info/dependency_links.txt
sparkfun_circuitpython_serlcd.egg-info/requires.txt
sparkfun_circuitpython_serlcd.egg-info/top_level.txt